{"nodes": [{"id": "d_creation_fine_finance_app_src_lib_redis_rate_limit_ts", "label": "rate-limit.ts", "file_type": "code", "source_file": "D:\\Creation\\Fine Finance App\\src\\lib\\redis\\rate-limit.ts", "source_location": "L1"}, {"id": "redis_rate_limit_checkratelimit", "label": "checkRateLimit()", "file_type": "code", "source_file": "D:\\Creation\\Fine Finance App\\src\\lib\\redis\\rate-limit.ts", "source_location": "L16"}], "edges": [{"source": "d_creation_fine_finance_app_src_lib_redis_rate_limit_ts", "target": "d_creation_fine_finance_app_src_lib_redis_client", "relation": "imports_from", "context": "import", "confidence": "EXTRACTED", "source_file": "D:\\Creation\\Fine Finance App\\src\\lib\\redis\\rate-limit.ts", "source_location": "L1", "weight": 1.0}, {"source": "d_creation_fine_finance_app_src_lib_redis_rate_limit_ts", "target": "redis_client_redis", "relation": "imports", "context": "import", "confidence": "EXTRACTED", "source_file": "D:\\Creation\\Fine Finance App\\src\\lib\\redis\\rate-limit.ts", "source_location": "L1", "weight": 1.0}, {"source": "d_creation_fine_finance_app_src_lib_redis_rate_limit_ts", "target": "redis_rate_limit_checkratelimit", "relation": "contains", "confidence": "EXTRACTED", "source_file": "D:\\Creation\\Fine Finance App\\src\\lib\\redis\\rate-limit.ts", "source_location": "L16", "weight": 1.0}], "raw_calls": [{"caller_nid": "redis_rate_limit_checkratelimit", "callee": "incr", "is_member_call": true, "source_file": "D:\\Creation\\Fine Finance App\\src\\lib\\redis\\rate-limit.ts", "source_location": "L24"}, {"caller_nid": "redis_rate_limit_checkratelimit", "callee": "expire", "is_member_call": true, "source_file": "D:\\Creation\\Fine Finance App\\src\\lib\\redis\\rate-limit.ts", "source_location": "L28"}, {"caller_nid": "redis_rate_limit_checkratelimit", "callee": "ttl", "is_member_call": true, "source_file": "D:\\Creation\\Fine Finance App\\src\\lib\\redis\\rate-limit.ts", "source_location": "L32"}, {"caller_nid": "redis_rate_limit_checkratelimit", "callee": "now", "is_member_call": true, "source_file": "D:\\Creation\\Fine Finance App\\src\\lib\\redis\\rate-limit.ts", "source_location": "L33"}, {"caller_nid": "redis_rate_limit_checkratelimit", "callee": "max", "is_member_call": true, "source_file": "D:\\Creation\\Fine Finance App\\src\\lib\\redis\\rate-limit.ts", "source_location": "L38"}]}